hudman/__init__.py
hudman/dnmanager.py
hudman/exceptions.py
hudman/headertime.py
hudman/messages.py
hudman/settings.py
hudman/app/__init__.py
hudman/app/run.py
hudman/hud/__init__.py
hudman/hud/factory.py
hudman/hud/github.py
hudman/hud/other.py
hudman-9.0.0.dist-info/LICENSE
hudman-9.0.0.dist-info/METADATA
hudman-9.0.0.dist-info/WHEEL
hudman-9.0.0.dist-info/entry_points.txt
hudman-9.0.0.dist-info/top_level.txt
hudman-9.0.0.dist-info/RECORD
