Metadata-Version: 2.1
Name: hudman
Version: 9.0.0
Summary: HUD Manager is a simple tool for creating a local HUD mirror
Author-email: Vitaly Zaitsev <vitaly@easycoding.org>
License: GPL-3.0-or-later
Project-URL: homepage, https://github.com/xvitaly/hudman
Project-URL: documentation, https://github.com/xvitaly/hudman/blob/master/docs/README.md
Project-URL: repository, https://github.com/xvitaly/hudman
Keywords: hud,hud-database,hud-manager,manager,mirror,tf2,tf2-hud,tool,utility
Classifier: Programming Language :: Python :: 3
Classifier: License :: OSI Approved :: GNU General Public License v3 (GPLv3)
Classifier: Operating System :: OS Independent
Requires-Python: >=3.6
License-File: LICENSE
Requires-Dist: defusedxml (>=0.7.0)
Requires-Dist: requests (>=2.22.0)
Provides-Extra: deploy
Requires-Dist: pyinstaller (>=5.7.0) ; extra == 'deploy'
Provides-Extra: test
Requires-Dist: tox (>=3.27.0) ; extra == 'test'
